TeachableMachineEasy/__init__.py
TeachableMachineEasy-0.0.6.dist-info/LICENSE
TeachableMachineEasy-0.0.6.dist-info/METADATA
TeachableMachineEasy-0.0.6.dist-info/WHEEL
TeachableMachineEasy-0.0.6.dist-info/top_level.txt
TeachableMachineEasy-0.0.6.dist-info/RECORD
