Metadata-Version: 2.1
Name: TeachableMachineEasy
Version: 0.0.6
Summary: This package allows you to connect teachable machine with python in a very simple way.
Home-page: https://repl.it/@EpicCodeWizard/Module-Source-Code
Author: Sarvesh Madullapalli
Author-email: sarveshsaharsh@gmail.com
License: UNKNOWN
Platform: UNKNOWN
Classifier: Programming Language :: Python :: 3
Classifier: License :: OSI Approved :: MIT License
Classifier: Operating System :: OS Independent
Requires-Python: >=3.6
